<?xml version="1.0" encoding="UTF-8"?>
<symbol name="BREVE_REST.DECORATED" interline="16">
    <bitmap>
	<row>---------------------------------------</row>
	<row>---------------------------------------</row>
	<row>+++++++++++++++++++++++++++++++++++++++</row>
        <row>----------###################----------</row>
        <row>----------###################----------</row>
        <row>----------###################----------</row>
        <row>----------###################----------</row>
        <row>----------###################----------</row>
        <row>----------###################----------</row>
        <row>----------###################----------</row>
        <row>----------###################----------</row>
        <row>----------###################----------</row>
        <row>----------###################----------</row>
        <row>----------###################----------</row>
        <row>----------###################----------</row>
        <row>----------###################----------</row>
        <row>----------###################----------</row>
        <row>----------###################----------</row>
	<row>+++++++++++++++++++++++++++++++++++++++</row>
	<row>---------------------------------------</row>
	<row>---------------------------------------</row>
    </bitmap>
</symbol>
