<?xml version="1.0" encoding="UTF-8" standalone="yes"?>
<sample id="559" interline="18" left="1098" top="1862" shape="ONE_16TH_REST">
    <run-table orientation="VERTICAL" width="24" height="55">
        <sequences>
            <item>0 27 3</item>
            <item>0 25 7</item>
            <item>0 24 10</item>
            <item>0 23 11</item>
            <item>0 22 15</item>
            <item>0 8 4 10 15</item>
            <item>0 6 8 8 15</item>
            <item>0 5 10 7 15</item>
            <item>0 4 12 6 15</item>
            <item>0 4 12 7 14 16 2</item>
            <item>16 8 10 16 5</item>
            <item>16 9 9 13 8</item>
            <item>16 14 3 11 9</item>
            <item>0 4 12 13 4 8 8</item>
            <item>0 4 12 13 3 5 8</item>
            <item>0 5 10 13 3 2 9</item>
            <item>0 7 8 12 10</item>
            <item>0 11 3 11 9</item>
            <item>0 10 4 8 8</item>
            <item>0 10 3 4 9</item>
            <item>0 9 3 2 9</item>
            <item>0 8 9</item>
            <item>0 7 8</item>
            <item>0 6 5</item>
        </sequences>
    </run-table>
</sample>
