<?xml version="1.0" encoding="UTF-8" standalone="yes"?>
<sample id="228" interline="22" left="403" top="630" shape="SHARP">
    <run-table orientation="VERTICAL" width="22" height="63">
        <sequences>
            <item>0 20 2 3 1 16 3</item>
            <item>0 19 8 14 9</item>
            <item>0 18 9 13 10</item>
            <item>0 17 10 13 9</item>
            <item>0 17 9 13 10</item>
            <item>0 6 56</item>
            <item>0 5 58</item>
            <item>0 16 12 1 34</item>
            <item>0 16 9 13 10 3 8</item>
            <item>0 15 10 13 9 7 2</item>
            <item>0 15 9 13 10</item>
            <item>0 15 9 13 10</item>
            <item>0 14 10 13 9</item>
            <item>0 14 9 13 10</item>
            <item>0 1 45 5 1</item>
            <item>55</item>
            <item>0 13 42</item>
            <item>0 13 9 10 13 6 1</item>
            <item>0 13 9 10 12</item>
            <item>0 12 9 11 12</item>
            <item>0 12 9 11 12</item>
            <item>0 32 11</item>
        </sequences>
    </run-table>
</sample>
